LICENSE
MANIFEST.in
README.rst
setup.cfg
setup.py
django_urlkeyword.egg-info/PKG-INFO
django_urlkeyword.egg-info/SOURCES.txt
django_urlkeyword.egg-info/dependency_links.txt
django_urlkeyword.egg-info/requires.txt
django_urlkeyword.egg-info/top_level.txt
urlkeyword/__init__.py
urlkeyword/validators.py