Metadata-Version: 1.1
Name: django-urlkeyword
Version: 0.1.1
Summary: Validate that your slugs do not match a keyword in your url 
Home-page: https://github.com/jleeothon/urlkeyword
Author: Johnny Lee
Author-email: jleeothon@outlook.com
License: MIT
Platform: UNKNOWN
Classifier: Environment :: Web Environment
Classifier: Framework :: Django
Classifier: Intended Audience :: Developers
Classifier: License :: OSI Approved :: MIT License
Classifier: Operating System :: OS Independent
Classifier: Programming Language :: Python
Classifier: Programming Language :: Python :: 3.4
Classifier: Topic :: Internet :: WWW/HTTP
Classifier: Topic :: Internet :: WWW/HTTP :: Dynamic Content
